Jamnsee/__init__.py
Jamnsee/module.py
Jamnsee-0.2.dist-info/LICENSE
Jamnsee-0.2.dist-info/METADATA
Jamnsee-0.2.dist-info/WHEEL
Jamnsee-0.2.dist-info/top_level.txt
Jamnsee-0.2.dist-info/RECORD
