Metadata-Version: 2.1
Name: Jamnsee
Version: 0.2
Summary: JynPopMod Python Module
Home-page: https://github.com/Jynoqtra/JynPopMod
Author: Jynoqtra
Author-email: Jynoqtra@gmail.com
Classifier: Programming Language :: Python :: 3
Classifier: License :: OSI Approved :: MIT License
Classifier: Intended Audience :: Developers
License-File: LICENSE
Requires-Dist: opencv-python
Requires-Dist: pyautogui
